{
  "ingredients": [],
  "tools": [
    {
      "name": "hammer",
      "image": "Assets/Sprites/hammer.png"
    },
    {
      "name": "string",
      "image": "Assets/Sprites/string.png"
    },
    {
      "name": "tail_piece",
      "image": "Assets/Sprites/kite_broken_part_3.png"
    }
  ],
  "initial": 3,
  "final": 0,
  "states": [
    {
      "id": 0,
      "image": "Assets/Sprites/vase_broken_2.png",
      "allow_tool_id": [
        "glue"
      ],
      "crit_tool_id": [
        "Plunger"
      ],
      "jsonToLoad": "Assets/Json/vase_proken_part_4.json"
    },
    {
      "id": 1,
      "image": ""
    },
    {
      "id": 2,
      "image": "Assets/Sprites/blank.png",
	  "crit_tool_id": [
        "tail_piece"
      ],
	  "jsonToLoad": "Assets/Json/kite_broken_part_2.json"
    },
    {
      "id": 3,
      "image": "",
      "allow_tool_id": [
        "hammer","glue"
      ],
      "crit_tool_id": [
        "Sand"
      ],
      "jsonToLoad": "Assets/Json/time_broken_part_2.json"
    }
  ]
}